quantworks/ext/bitcoincharts/__init__.py
quantworks/ext/bitcoincharts/barfeed.py
quantworks/ext/bitstamp/__init__.py
quantworks/ext/bitstamp/barfeed.py
quantworks/ext/bitstamp/broker.py
quantworks/ext/bitstamp/common.py
quantworks/ext/bitstamp/httpclient.py
quantworks/ext/bitstamp/livebroker.py
quantworks/ext/bitstamp/livefeed.py
quantworks/ext/bitstamp/wsclient.py
quantworks_bitcoin-1.0.dist-info/WHEEL
quantworks_bitcoin-1.0.dist-info/METADATA
quantworks_bitcoin-1.0.dist-info/RECORD
